parvus/__init__.py
parvus/__main__.py
parvus/parvus.py
parvus-0.1.1.dist-info/LICENSE
parvus-0.1.1.dist-info/METADATA
parvus-0.1.1.dist-info/WHEEL
parvus-0.1.1.dist-info/entry_points.txt
parvus-0.1.1.dist-info/top_level.txt
parvus-0.1.1.dist-info/RECORD
